flexBlock/__init__.py
flexBlock/common.py
flexBlock/blockchain/__init__.py
flexBlock/blockchain/blockchain.py
flexBlock/pool/__init__.py
flexBlock/pool/decorators.py
flexBlock/pool/pool.py
flexBlock/pool/primitives.py
flexBlock/pool/utils.py
tests/__init__.py
tests/pool/__init__.py
tests/pool/test_pool.py
flexBlock-0.0.1.dist-info/LICENSE.txt
flexBlock-0.0.1.dist-info/METADATA
flexBlock-0.0.1.dist-info/WHEEL
flexBlock-0.0.1.dist-info/top_level.txt
flexBlock-0.0.1.dist-info/RECORD
