Metadata-Version: 2.1
Name: flexBlock
Version: 0.0.1
Home-page: https://github.com/FLEXible-FL/flex-block
Author: Mario Garcia Marquez
Author-email: mariogarciamarq@gmail.com
Keywords: blockchain FL federated-learning flexible
Classifier: Development Status :: 4 - Beta
Classifier: Intended Audience :: Science/Research
Classifier: Topic :: Software Development :: Build Tools
Classifier: License :: OSI Approved :: GNU Affero General Public License v3 or later (AGPLv3+)
Classifier: Programming Language :: Python :: 3
Classifier: Programming Language :: Python :: 3.8
Classifier: Programming Language :: Python :: 3.9
Classifier: Programming Language :: Python :: 3.10
Classifier: Programming Language :: Python :: 3.11
Classifier: Programming Language :: Python :: 3 :: Only
Requires-Python: >=3.8.10
License-File: LICENSE.txt
Requires-Dist: flexible-fl
